README.rst
setup.py
aws_visualizer/__init__.py
aws_visualizer.egg-info/PKG-INFO
aws_visualizer.egg-info/SOURCES.txt
aws_visualizer.egg-info/dependency_links.txt
aws_visualizer.egg-info/entry_points.txt
aws_visualizer.egg-info/not-zip-safe
aws_visualizer.egg-info/requires.txt
aws_visualizer.egg-info/top_level.txt
aws_visualizer/dot/__init__.py
aws_visualizer/dot/graph_region.py
aws_visualizer/neo4j/__init__.py
aws_visualizer/neo4j/ec2_instance.py
aws_visualizer/neo4j/elb.py
aws_visualizer/neo4j/elbv2.py
aws_visualizer/neo4j/function.py
aws_visualizer/neo4j/main.py
aws_visualizer/neo4j/rds.py
aws_visualizer/neo4j/redshift.py
aws_visualizer/neo4j/security_group.py
aws_visualizer/neo4j/sts.py