Metadata-Version: 1.0
Name: aws-visualizer
Version: 0.1.0
Summary: A visualizer of the network of security group dependencies in an AWS VPC.
Home-page: https://github.com/mvanholsteijn/aws-visualizer
Author: Mark van Holsteijn
Author-email: mark@binx.io
License: UNKNOWN
Platform: any
